odoo/addons/account_invoice_google_document_ai_purchase/README.rst
odoo/addons/account_invoice_google_document_ai_purchase/__init__.py
odoo/addons/account_invoice_google_document_ai_purchase/__manifest__.py
odoo/addons/account_invoice_google_document_ai_purchase/i18n/account_invoice_google_document_ai_purchase.pot
odoo/addons/account_invoice_google_document_ai_purchase/i18n/it.po
odoo/addons/account_invoice_google_document_ai_purchase/models/__init__.py
odoo/addons/account_invoice_google_document_ai_purchase/models/account_move_google_document_ai.py
odoo/addons/account_invoice_google_document_ai_purchase/readme/CONTRIBUTORS.rst
odoo/addons/account_invoice_google_document_ai_purchase/readme/DESCRIPTION.rst
odoo/addons/account_invoice_google_document_ai_purchase/static/description/icon.png
odoo/addons/account_invoice_google_document_ai_purchase/static/description/index.html
odoo/addons/account_invoice_google_document_ai_purchase/tests/__init__.py
odoo/addons/account_invoice_google_document_ai_purchase/tests/result.json
odoo/addons/account_invoice_google_document_ai_purchase/tests/test_google_document_ai.py
odoo14_addon_account_invoice_google_document_ai_purchase-14.0.1.0.1.dev5.dist-info/METADATA
odoo14_addon_account_invoice_google_document_ai_purchase-14.0.1.0.1.dev5.dist-info/WHEEL
odoo14_addon_account_invoice_google_document_ai_purchase-14.0.1.0.1.dev5.dist-info/top_level.txt
odoo14_addon_account_invoice_google_document_ai_purchase-14.0.1.0.1.dev5.dist-info/RECORD
